everest/__init__.py
everest/abighelp.py
everest/events.py
everest/everest.py
everest/ladybower.py
everest/monitor.py
everest/potluck.py
everest_climber-0.0.3.dist-info/DESCRIPTION.rst
everest_climber-0.0.3.dist-info/METADATA
everest_climber-0.0.3.dist-info/RECORD
everest_climber-0.0.3.dist-info/WHEEL
everest_climber-0.0.3.dist-info/dependency_links.txt
everest_climber-0.0.3.dist-info/metadata.json
everest_climber-0.0.3.dist-info/top_level.txt
