Metadata-Version: 2.0
Name: everest-climber
Version: 0.0.3
Summary: Simple event simulation framework
Home-page: https://github.com/peakrisk/everest
Author: John Gill
Author-email: swfiua@gmail.com
License: BSD
Download-URL: https://github.com/peakrisk/everest/tarball/0.0.3
Platform: UNKNOWN
Classifier: Development Status :: 3 - Alpha
Classifier: Intended Audience :: Developers
Classifier: Programming Language :: Python :: 3
Requires-Dist: networkx
Requires-Dist: pandas
Requires-Dist: ripl
